redpepper/agent/__init__.py
redpepper/agent/__main__.py
redpepper/agent/agent.py
redpepper/agent/agent.yml
redpepper/agent/config.py
redpepper/agent/entrypoint.py
redpepper_agent-0.3.3.dist-info/METADATA
redpepper_agent-0.3.3.dist-info/WHEEL
redpepper_agent-0.3.3.dist-info/entry_points.txt
redpepper_agent-0.3.3.dist-info/RECORD
