Metadata-Version: 2.4
Name: redpepper-agent
Version: 0.3.3
Summary: A state-based server management system (agent package)
License: MIT License
Classifier: Development Status :: 3 - Alpha
Classifier: Intended Audience :: Developers
Classifier: Intended Audience :: Information Technology
Classifier: License :: OSI Approved :: MIT License
Classifier: Operating System :: POSIX :: Linux
Classifier: Programming Language :: Python :: 3
Classifier: Topic :: System :: Installation/Setup
Classifier: Topic :: System :: Systems Administration
Requires-Python: >=3.12
Requires-Dist: pyyaml>=6.0.2
Requires-Dist: redpepper
Requires-Dist: redpepper-common
Requires-Dist: trio>=0.26.2
